starvex/__init__.py
starvex/cli.py
starvex/core.py
starvex/guard.py
starvex/instrument.py
starvex/models.py
starvex/rules.py
starvex/utils.py
starvex/_internals/__init__.py
starvex/_internals/auto_fix_pipeline.py
starvex/_internals/engine_eval.py
starvex/_internals/engine_nemo.py
starvex/_internals/hybrid_router.py
starvex/_internals/nli_engine.py
starvex/_internals/pii_engine.py
starvex/_internals/pinecone_router.py
starvex/_internals/semantic_router.py
starvex/_internals/tracer.py
starvex/_internals/nemo_guardrails/config.yml
starvex-2.3.0.dist-info/METADATA
starvex-2.3.0.dist-info/WHEEL
starvex-2.3.0.dist-info/entry_points.txt
starvex-2.3.0.dist-info/RECORD
