Metadata-Version: 2.4
Name: starvex
Version: 2.3.0
Summary: Starvex - Production-ready AI agents with semantic guardrails, observability, and security
Project-URL: Homepage, https://starvex.in
Project-URL: Documentation, https://starvex.in/docs
Project-URL: Dashboard, https://starvex.in/dashboard
Project-URL: Repository, https://github.com/starvex/starvex-python
Project-URL: Issues, https://github.com/starvex/starvex-python/issues
Author-email: Starvex Team <team@starvex.in>
License: MIT
Keywords: agents,ai,embeddings,evaluation,guardrails,llm,nli,observability,safety,security,semantic
Classifier: Development Status :: 4 - Beta
Classifier: Intended Audience :: Developers
Classifier: License :: OSI Approved :: MIT License
Classifier: Operating System :: OS Independent
Classifier: Programming Language :: Python :: 3
Classifier: Programming Language :: Python :: 3.9
Classifier: Programming Language :: Python :: 3.10
Classifier: Programming Language :: Python :: 3.11
Classifier: Programming Language :: Python :: 3.12
Classifier: Topic :: Scientific/Engineering :: Artificial Intelligence
Classifier: Topic :: Security
Requires-Python: >=3.9
Requires-Dist: httpx>=0.24.0
Requires-Dist: pydantic>=2.0.0
Requires-Dist: rich>=13.0.0
Provides-Extra: dev
Requires-Dist: black>=23.0.0; extra == 'dev'
Requires-Dist: mypy>=1.0.0; extra == 'dev'
Requires-Dist: pytest-asyncio>=0.21.0; extra == 'dev'
Requires-Dist: pytest-cov>=4.0.0; extra == 'dev'
Requires-Dist: pytest>=7.0.0; extra == 'dev'
Requires-Dist: ruff>=0.1.0; extra == 'dev'
Provides-Extra: eval
Requires-Dist: deepeval>=0.21.0; extra == 'eval'
Provides-Extra: full
Requires-Dist: deepeval>=0.21.0; extra == 'full'
Requires-Dist: nemoguardrails>=0.8.0; extra == 'full'
Requires-Dist: pinecone-client>=3.0.0; extra == 'full'
Requires-Dist: presidio-analyzer>=2.2.0; extra == 'full'
Requires-Dist: presidio-anonymizer>=2.2.0; extra == 'full'
Requires-Dist: torch>=2.0.0; extra == 'full'
Requires-Dist: transformers>=4.30.0; extra == 'full'
Provides-Extra: guardrails
Requires-Dist: nemoguardrails>=0.8.0; extra == 'guardrails'
Provides-Extra: hybrid
Requires-Dist: deepeval>=0.21.0; extra == 'hybrid'
Requires-Dist: langfuse>=2.0.0; extra == 'hybrid'
Requires-Dist: numpy>=1.21.0; extra == 'hybrid'
Requires-Dist: sentence-transformers>=2.2.0; extra == 'hybrid'
Provides-Extra: nli
Requires-Dist: torch>=2.0.0; extra == 'nli'
Requires-Dist: transformers>=4.30.0; extra == 'nli'
Provides-Extra: pii
Requires-Dist: presidio-analyzer>=2.2.0; extra == 'pii'
Requires-Dist: presidio-anonymizer>=2.2.0; extra == 'pii'
Provides-Extra: semantic
Requires-Dist: numpy>=1.21.0; extra == 'semantic'
Requires-Dist: sentence-transformers>=2.2.0; extra == 'semantic'
Provides-Extra: vector
Requires-Dist: pinecone-client>=3.0.0; extra == 'vector'
